{
  "frameWidth": 224,
  "frameHeight": 224,
  "frameDuration": 100,
  "extraX": 0.0,
  "extraY": 0.0,
  "lists": {
    "frames": [
      {
        "x": 675,
        "y": 225
      },
      {
        "x": 1350,
        "y": 450
      },
      {
        "x": 1350,
        "y": 225
      },
      {
        "x": 1350,
        "y": 0
      },
      {
        "x": 1125,
        "y": 675
      },
      {
        "x": 1125,
        "y": 450
      },
      {
        "x": 1125,
        "y": 225
      },
      {
        "x": 1125,
        "y": 0
      },
      {
        "x": 900,
        "y": 675
      },
      {
        "x": 900,
        "y": 450
      },
      {
        "x": 900,
        "y": 225
      },
      {
        "x": 900,
        "y": 0
      },
      {
        "x": 675,
        "y": 675
      },
      {
        "x": 675,
        "y": 450
      },
      {
        "x": 1350,
        "y": 675
      },
      {
        "x": 675,
        "y": 0
      },
      {
        "x": 450,
        "y": 675
      },
      {
        "x": 450,
        "y": 450
      },
      {
        "x": 450,
        "y": 225
      },
      {
        "x": 450,
        "y": 0
      },
      {
        "x": 225,
        "y": 675
      },
      {
        "x": 225,
        "y": 450
      },
      {
        "x": 225,
        "y": 225
      },
      {
        "x": 225,
        "y": 0
      },
      {
        "x": 0,
        "y": 675
      },
      {
        "x": 0,
        "y": 450
      },
      {
        "x": 0,
        "y": 225
      },
      {
        "x": 0,
        "y": 0
      }
    ]
  }
}