{
  "frameWidth": 12,
  "frameHeight": 10,
  "frameDuration": 100,
  "extraX": 0.0,
  "extraY": 0.0,
  "lists": {
    "frames": [
      {
        "x": 0,
        "y": 175
      },
      {
        "x": 0,
        "y": 0
      },
      {
        "x": 0,
        "y": 35
      },
      {
        "x": 0,
        "y": 70
      },
      {
        "x": 0,
        "y": 105
      },
      {
        "x": 0,
        "y": 140
      },
      {
        "x": 0,
        "y": 210
      },
      {
        "x": 57,
        "y": 35
      },
      {
        "x": 57,
        "y": 0
      },
      {
        "x": 112,
        "y": 111
      },
      {
        "x": 112,
        "y": 70
      },
      {
        "x": 57,
        "y": 193
      },
      {
        "x": 114,
        "y": 0
      },
      {
        "x": 114,
        "y": 0
      },
      {
        "x": 57,
        "y": 111
      },
      {
        "x": 57,
        "y": 152
      },
      {
        "x": 112,
        "y": 193
      },
      {
        "x": 112,
        "y": 152
      },
      {
        "x": 57,
        "y": 70
      },
      {
        "x": 26,
        "y": 245
      },
      {
        "x": 0,
        "y": 245
      },
      {
        "x": 13,
        "y": 245
      },
      {
        "x": 57,
        "y": 234
      },
      {
        "x": 39,
        "y": 245
      },
      {
        "x": 52,
        "y": 245
      }
    ]
  }
}